{
  "did": "did:plc:nrxngnjnce74aisq4hiu5zuy",
  "time_us": 1743946675026613,
  "kind": "commit",
  "commit": {
    "rev": "3lm5kx2ikwh2r",
    "operation": "create",
    "collection": "app.bsky.feed.post",
    "rkey": "3lm5kwyttt22n",
    "record": {
      "$type": "app.bsky.feed.post",
      "createdAt": "2025-04-06T13:37:52.542Z",
      "embed": {
        "$type": "app.bsky.embed.images",
        "images": [
          {
            "alt": "",
            "aspectRatio": {
              "height": 1505,
              "width": 2000
            },
            "image": {
              "$type": "blob",
              "ref": {
                "$link": "bafkreibqwcxgkzev64cgmz5tosrcvi5wcwvgg7ydbkoyvdkrx3bhgbtniq"
              },
              "mimeType": "image/jpeg",
              "size": 466950
            }
          }
        ]
      },
      "facets": [
        {
          "features": [
            {
              "$type": "app.bsky.richtext.facet#tag",
              "tag": "PSHSummit"
            }
          ],
          "index": {
            "byteEnd": 23,
            "byteStart": 13
          }
        }
      ],
      "langs": [
        "en"
      ],
      "text": "On my way to #PSHSummit (ORD -> SEA). Super pumped even though this is way too early for a Sunday 😅 Let's go!"
    },
    "cid": "bafyreihu7u23r6joc3wh6mog7tilpmihc2tswhjpuwc7bdoecxndy53yoy"
  }
}